[
  {
    "op": "core/column-addition",
    "engineConfig": {
      "facets": [],
      "mode": "row-based"
    },
    "baseColumnName": "Name",
    "expression": "grel:if (value.contains(/Church/), \"Church\", \"\")",
    "onError": "set-to-blank",
    "newColumnName": "Church",
    "columnInsertIndex": 3,
    "description": "Create column Church at index 3 based on column Name using expression grel:if (value.contains(/Church/), \"Church\", \"\")"
  },
  {
    "op": "core/text-transform",
    "engineConfig": {
      "facets": [
        {
          "type": "list",
          "name": "Orig-copy",
          "expression": "grel:value.contains(\"Chapel\")",
          "columnName": "Orig-copy",
          "invert": false,
          "omitBlank": false,
          "omitError": false,
          "selection": [
            {
              "v": {
                "v": true,
                "l": "true"
              }
            }
          ],
          "selectBlank": false,
          "selectError": false
        }
      ],
      "mode": "row-based"
    },
    "columnName": "Church",
    "expression": "grel:if (cells[\"Orig-copy\"].value.contains(/Chapel/), \"Church\", \"\")",
    "onError": "keep-original",
    "repeat": false,
    "repeatCount": 10,
    "description": "Text transform on cells in column Church using expression grel:if (cells[\"Orig-copy\"].value.contains(/Chapel/), \"Church\", \"\")"
  },
  {
    "op": "core/text-transform",
    "engineConfig": {
      "facets": [
        {
          "type": "list",
          "name": "Orig-copy",
          "expression": "grel:value.contains(\"Tabernacle\")",
          "columnName": "Orig-copy",
          "invert": false,
          "omitBlank": false,
          "omitError": false,
          "selection": [
            {
              "v": {
                "v": true,
                "l": "true"
              }
            }
          ],
          "selectBlank": false,
          "selectError": false
        }
      ],
      "mode": "row-based"
    },
    "columnName": "Church",
    "expression": "grel:if (cells[\"Orig-copy\"].value.contains(/Tabernacle/), \"Church\", \"\")",
    "onError": "keep-original",
    "repeat": false,
    "repeatCount": 10,
    "description": "Text transform on cells in column Church using expression grel:if (cells[\"Orig-copy\"].value.contains(/Tabernacle/), \"Church\", \"\")"
  },
  {
    "op": "core/text-transform",
    "engineConfig": {
      "facets": [
        {
          "type": "list",
          "name": "Church",
          "expression": "value",
          "columnName": "Church",
          "invert": false,
          "omitBlank": false,
          "omitError": false,
          "selection": [],
          "selectBlank": true,
          "selectError": false
        },
        {
          "type": "list",
          "name": "Church denomination",
          "expression": "value",
          "columnName": "Church denomination",
          "invert": false,
          "omitBlank": false,
          "omitError": false,
          "selection": [],
          "selectBlank": true,
          "selectError": false
        }
      ],
      "mode": "row-based"
    },
    "columnName": "Church",
    "expression": "grel:if (cells[\"Orig-copy\"].value.contains(/Salvation Army/), \"Church\", \"\")",
    "onError": "keep-original",
    "repeat": false,
    "repeatCount": 10,
    "description": "Text transform on cells in column Church using expression grel:if (cells[\"Orig-copy\"].value.contains(/Salvation Army/), \"Church\", \"\")"
  },
  {
    "op": "core/text-transform",
    "engineConfig": {
      "facets": [
        {
          "type": "list",
          "name": "Church",
          "expression": "value",
          "columnName": "Church",
          "invert": false,
          "omitBlank": false,
          "omitError": false,
          "selection": [],
          "selectBlank": true,
          "selectError": false
        }
      ],
      "mode": "row-based"
    },
    "columnName": "Church",
    "expression": "grel:if (cells[\"Orig-copy\"].value.contains(/Brotherhood/), \"Church\", \"\")",
    "onError": "keep-original",
    "repeat": false,
    "repeatCount": 10,
    "description": "Text transform on cells in column Church using expression grel:if (cells[\"Orig-copy\"].value.contains(/Brotherhood/), \"Church\", \"\")"
  },
  {
    "op": "core/text-transform",
    "engineConfig": {
      "facets": [
        {
          "type": "list",
          "name": "Church",
          "expression": "value",
          "columnName": "Church",
          "invert": false,
          "omitBlank": false,
          "omitError": false,
          "selection": [
            {
              "v": {
                "v": "Church",
                "l": "Church"
              }
            }
          ],
          "selectBlank": false,
          "selectError": false
        },
        {
          "type": "list",
          "name": "Title",
          "expression": "value",
          "columnName": "Title",
          "invert": false,
          "omitBlank": false,
          "omitError": false,
          "selection": [
            {
              "v": {
                "v": "Rev",
                "l": "Rev"
              }
            }
          ],
          "selectBlank": false,
          "selectError": false
        }
      ],
      "mode": "row-based"
    },
    "columnName": "Church",
    "expression": "grel:if (cells[\"Title\"].value.contains(/Rev/), \"\", \"\")",
    "onError": "keep-original",
    "repeat": false,
    "repeatCount": 10,
    "description": "Text transform on cells in column Church using expression grel:if (cells[\"Title\"].value.contains(/Rev/), \"\", \"\")"
  },
  {
    "op": "core/column-addition",
    "engineConfig": {
      "facets": [
        {
          "type": "list",
          "name": "Church",
          "expression": "value",
          "columnName": "Church",
          "invert": false,
          "omitBlank": false,
          "omitError": false,
          "selection": [
            {
              "v": {
                "v": "Church",
                "l": "Church"
              }
            }
          ],
          "selectBlank": false,
          "selectError": false
        }
      ],
      "mode": "row-based"
    },
    "baseColumnName": "Name",
    "expression": "grel:if (cells[\"Name\"].value.contains(/Baptist/), \"Baptist\", \"\")",
    "onError": "set-to-blank",
    "newColumnName": "Church denomination",
    "columnInsertIndex": 3,
    "description": "Create column Church denomination at index 3 based on column Name using expression grel:if (cells[\"Name\"].value.contains(/Baptist/), \"Baptist\", \"\")"
  },
  {
    "op": "core/column-move",
    "columnName": "Church denomination",
    "index": 4,
    "description": "Move column Church denomination to position 4"
  },
  {
    "op": "core/text-transform",
    "engineConfig": {
      "facets": [
        {
          "type": "list",
          "name": "Church",
          "expression": "value",
          "columnName": "Church",
          "invert": false,
          "omitBlank": false,
          "omitError": false,
          "selection": [
            {
              "v": {
                "v": "Church",
                "l": "Church"
              }
            }
          ],
          "selectBlank": false,
          "selectError": false
        },
        {
          "type": "list",
          "name": "Church denomination",
          "expression": "value",
          "columnName": "Church denomination",
          "invert": false,
          "omitBlank": false,
          "omitError": false,
          "selection": [],
          "selectBlank": true,
          "selectError": false
        }
      ],
      "mode": "row-based"
    },
    "columnName": "Church denomination",
    "expression": "grel:if (cells[\"Name\"].value.contains(/Catholic/), \"Catholic\", \"\")",
    "onError": "keep-original",
    "repeat": false,
    "repeatCount": 10,
    "description": "Text transform on cells in column Church denomination using expression grel:if (cells[\"Name\"].value.contains(/Catholic/), \"Catholic\", \"\")"
  },
  {
    "op": "core/text-transform",
    "engineConfig": {
      "facets": [
        {
          "type": "list",
          "name": "Church",
          "expression": "value",
          "columnName": "Church",
          "invert": false,
          "omitBlank": false,
          "omitError": false,
          "selection": [
            {
              "v": {
                "v": "Church",
                "l": "Church"
              }
            }
          ],
          "selectBlank": false,
          "selectError": false
        },
        {
          "type": "list",
          "name": "Church denomination",
          "expression": "value",
          "columnName": "Church denomination",
          "invert": false,
          "omitBlank": false,
          "omitError": false,
          "selection": [],
          "selectBlank": true,
          "selectError": false
        }
      ],
      "mode": "row-based"
    },
    "columnName": "Church denomination",
    "expression": "grel:if (cells[\"Name\"].value.contains(/Congregational/), \"Congregational\", \"\")",
    "onError": "keep-original",
    "repeat": false,
    "repeatCount": 10,
    "description": "Text transform on cells in column Church denomination using expression grel:if (cells[\"Name\"].value.contains(/Congregational/), \"Congregational\", \"\")"
  },
  {
    "op": "core/text-transform",
    "engineConfig": {
      "facets": [
        {
          "type": "list",
          "name": "Church",
          "expression": "value",
          "columnName": "Church",
          "invert": false,
          "omitBlank": false,
          "omitError": false,
          "selection": [
            {
              "v": {
                "v": "Church",
                "l": "Church"
              }
            }
          ],
          "selectBlank": false,
          "selectError": false
        },
        {
          "type": "list",
          "name": "Church denomination",
          "expression": "value",
          "columnName": "Church denomination",
          "invert": false,
          "omitBlank": false,
          "omitError": false,
          "selection": [],
          "selectBlank": true,
          "selectError": false
        }
      ],
      "mode": "row-based"
    },
    "columnName": "Church denomination",
    "expression": "grel:if (cells[\"Name\"].value.contains(/Episcopal/), \"Episcopal\", \"\")",
    "onError": "keep-original",
    "repeat": false,
    "repeatCount": 10,
    "description": "Text transform on cells in column Church denomination using expression grel:if (cells[\"Name\"].value.contains(/Episcopal/), \"Episcopal\", \"\")"
  },
  {
    "op": "core/text-transform",
    "engineConfig": {
      "facets": [
        {
          "type": "list",
          "name": "Church",
          "expression": "value",
          "columnName": "Church",
          "invert": false,
          "omitBlank": false,
          "omitError": false,
          "selection": [
            {
              "v": {
                "v": "Church",
                "l": "Church"
              }
            }
          ],
          "selectBlank": false,
          "selectError": false
        },
        {
          "type": "list",
          "name": "Church denomination",
          "expression": "value",
          "columnName": "Church denomination",
          "invert": false,
          "omitBlank": false,
          "omitError": false,
          "selection": [],
          "selectBlank": true,
          "selectError": false
        }
      ],
      "mode": "row-based"
    },
    "columnName": "Church denomination",
    "expression": "grel:if (cells[\"Name\"].value.contains(/Lutheran/), \"Lutheran\", \"\")",
    "onError": "keep-original",
    "repeat": false,
    "repeatCount": 10,
    "description": "Text transform on cells in column Church denomination using expression grel:if (cells[\"Name\"].value.contains(/Lutheran/), \"Lutheran\", \"\")"
  },
  {
    "op": "core/text-transform",
    "engineConfig": {
      "facets": [
        {
          "type": "list",
          "name": "Church",
          "expression": "value",
          "columnName": "Church",
          "invert": false,
          "omitBlank": false,
          "omitError": false,
          "selection": [
            {
              "v": {
                "v": "Church",
                "l": "Church"
              }
            }
          ],
          "selectBlank": false,
          "selectError": false
        },
        {
          "type": "list",
          "name": "Church denomination",
          "expression": "value",
          "columnName": "Church denomination",
          "invert": false,
          "omitBlank": false,
          "omitError": false,
          "selection": [],
          "selectBlank": true,
          "selectError": false
        }
      ],
      "mode": "row-based"
    },
    "columnName": "Church denomination",
    "expression": "grel:if (cells[\"Name\"].value.contains(/M E/), \"Methodist\", \"\")",
    "onError": "keep-original",
    "repeat": false,
    "repeatCount": 10,
    "description": "Text transform on cells in column Church denomination using expression grel:if (cells[\"Name\"].value.contains(/M E/), \"Methodist\", \"\")"
  },
  {
    "op": "core/text-transform",
    "engineConfig": {
      "facets": [
        {
          "type": "list",
          "name": "Church",
          "expression": "value",
          "columnName": "Church",
          "invert": false,
          "omitBlank": false,
          "omitError": false,
          "selection": [
            {
              "v": {
                "v": "Church",
                "l": "Church"
              }
            }
          ],
          "selectBlank": false,
          "selectError": false
        },
        {
          "type": "list",
          "name": "Church denomination",
          "expression": "value",
          "columnName": "Church denomination",
          "invert": false,
          "omitBlank": false,
          "omitError": false,
          "selection": [],
          "selectBlank": true,
          "selectError": false
        }
      ],
      "mode": "row-based"
    },
    "columnName": "Church denomination",
    "expression": "grel:if (cells[\"Name\"].value.contains(/ARP/), \"Associate Reformed Presbyterian\", \"\")",
    "onError": "keep-original",
    "repeat": false,
    "repeatCount": 10,
    "description": "Text transform on cells in column Church denomination using expression grel:if (cells[\"Name\"].value.contains(/ARP/), \"Associate Reformed Presbyterian\", \"\")"
  },
  {
    "op": "core/text-transform",
    "engineConfig": {
      "facets": [
        {
          "type": "list",
          "name": "Church",
          "expression": "value",
          "columnName": "Church",
          "invert": false,
          "omitBlank": false,
          "omitError": false,
          "selection": [
            {
              "v": {
                "v": "Church",
                "l": "Church"
              }
            }
          ],
          "selectBlank": false,
          "selectError": false
        },
        {
          "type": "list",
          "name": "Church denomination",
          "expression": "value",
          "columnName": "Church denomination",
          "invert": false,
          "omitBlank": false,
          "omitError": false,
          "selection": [],
          "selectBlank": true,
          "selectError": false
        }
      ],
      "mode": "row-based"
    },
    "columnName": "Church denomination",
    "expression": "grel:if (cells[\"Name\"].value.contains(/Presbyterian/), \"Presbyterian\", \"\")",
    "onError": "keep-original",
    "repeat": false,
    "repeatCount": 10,
    "description": "Text transform on cells in column Church denomination using expression grel:if (cells[\"Name\"].value.contains(/Presbyterian/), \"Presbyterian\", \"\")"
  },
  {
    "op": "core/text-transform",
    "engineConfig": {
      "facets": [
        {
          "type": "list",
          "name": "Church",
          "expression": "value",
          "columnName": "Church",
          "invert": false,
          "omitBlank": false,
          "omitError": false,
          "selection": [
            {
              "v": {
                "v": "Church",
                "l": "Church"
              }
            }
          ],
          "selectBlank": false,
          "selectError": false
        },
        {
          "type": "list",
          "name": "Church denomination",
          "expression": "value",
          "columnName": "Church denomination",
          "invert": false,
          "omitBlank": false,
          "omitError": false,
          "selection": [],
          "selectBlank": true,
          "selectError": false
        }
      ],
      "mode": "row-based"
    },
    "columnName": "Church denomination",
    "expression": "grel:if (cells[\"Name\"].value.contains(/Methodist/), \"Methodist\", \"\")",
    "onError": "keep-original",
    "repeat": false,
    "repeatCount": 10,
    "description": "Text transform on cells in column Church denomination using expression grel:if (cells[\"Name\"].value.contains(/Methodist/), \"Methodist\", \"\")"
  },
  {
    "op": "core/text-transform",
    "engineConfig": {
      "facets": [
        {
          "type": "list",
          "name": "Church",
          "expression": "value",
          "columnName": "Church",
          "invert": false,
          "omitBlank": false,
          "omitError": false,
          "selection": [
            {
              "v": {
                "v": "Church",
                "l": "Church"
              }
            }
          ],
          "selectBlank": false,
          "selectError": false
        },
        {
          "type": "list",
          "name": "Church denomination",
          "expression": "value",
          "columnName": "Church denomination",
          "invert": false,
          "omitBlank": false,
          "omitError": false,
          "selection": [],
          "selectBlank": true,
          "selectError": false
        }
      ],
      "mode": "row-based"
    },
    "columnName": "Church denomination",
    "expression": "grel:if (cells[\"Orig-copy\"].value.contains(/Meth/), \"Methodist\", \"\")",
    "onError": "keep-original",
    "repeat": false,
    "repeatCount": 10,
    "description": "Text transform on cells in column Church denomination using expression grel:if (cells[\"Orig-copy\"].value.contains(/Meth/), \"Methodist\", \"\")"
  },
  {
    "op": "core/text-transform",
    "engineConfig": {
      "facets": [
        {
          "type": "list",
          "name": "Church",
          "expression": "value",
          "columnName": "Church",
          "invert": false,
          "omitBlank": false,
          "omitError": false,
          "selection": [
            {
              "v": {
                "v": "Church",
                "l": "Church"
              }
            }
          ],
          "selectBlank": false,
          "selectError": false
        },
        {
          "type": "list",
          "name": "Church denomination",
          "expression": "value",
          "columnName": "Church denomination",
          "invert": false,
          "omitBlank": false,
          "omitError": false,
          "selection": [],
          "selectBlank": true,
          "selectError": false
        }
      ],
      "mode": "row-based"
    },
    "columnName": "Church denomination",
    "expression": "grel:if (cells[\"Orig-copy\"].value.contains(/Episc/), \"Episcopal\", \"\")",
    "onError": "keep-original",
    "repeat": false,
    "repeatCount": 10,
    "description": "Text transform on cells in column Church denomination using expression grel:if (cells[\"Orig-copy\"].value.contains(/Episc/), \"Episcopal\", \"\")"
  },
  {
    "op": "core/text-transform",
    "engineConfig": {
      "facets": [
        {
          "type": "list",
          "name": "Church",
          "expression": "value",
          "columnName": "Church",
          "invert": false,
          "omitBlank": false,
          "omitError": false,
          "selection": [
            {
              "v": {
                "v": "Church",
                "l": "Church"
              }
            }
          ],
          "selectBlank": false,
          "selectError": false
        },
        {
          "type": "list",
          "name": "Church denomination",
          "expression": "value",
          "columnName": "Church denomination",
          "invert": false,
          "omitBlank": false,
          "omitError": false,
          "selection": [],
          "selectBlank": true,
          "selectError": false
        }
      ],
      "mode": "row-based"
    },
    "columnName": "Church denomination",
    "expression": "grel:if (cells[\"Name\"].value.contains(/Salvation Army/), \"Non-denominational\", \"\")",
    "onError": "keep-original",
    "repeat": false,
    "repeatCount": 10,
    "description": "Text transform on cells in column Church denomination using expression grel:if (cells[\"Name\"].value.contains(/Salvation Army/), \"Non-denominational\", \"\")"
  },
  {
    "op": "core/text-transform",
    "engineConfig": {
      "facets": [
        {
          "type": "list",
          "name": "Church",
          "expression": "value",
          "columnName": "Church",
          "invert": false,
          "omitBlank": false,
          "omitError": false,
          "selection": [
            {
              "v": {
                "v": "Church",
                "l": "Church"
              }
            }
          ],
          "selectBlank": false,
          "selectError": false
        },
        {
          "type": "list",
          "name": "Church denomination",
          "expression": "value",
          "columnName": "Church denomination",
          "invert": false,
          "omitBlank": false,
          "omitError": false,
          "selection": [],
          "selectBlank": true,
          "selectError": false
        }
      ],
      "mode": "row-based"
    },
    "columnName": "Church denomination",
    "expression": "grel:if (cells[\"Orig-copy\"].value.contains(/undenominational/), \"Non-denominational\", \"\")",
    "onError": "keep-original",
    "repeat": false,
    "repeatCount": 10,
    "description": "Text transform on cells in column Church denomination using expression grel:if (cells[\"Orig-copy\"].value.contains(/undenominational/), \"Non-denominational\", \"\")"
  },
  {
    "op": "core/text-transform",
    "engineConfig": {
      "facets": [
        {
          "type": "list",
          "name": "Church",
          "expression": "value",
          "columnName": "Church",
          "invert": false,
          "omitBlank": false,
          "omitError": false,
          "selection": [
            {
              "v": {
                "v": "Church",
                "l": "Church"
              }
            }
          ],
          "selectBlank": false,
          "selectError": false
        },
        {
          "type": "list",
          "name": "Church denomination",
          "expression": "value",
          "columnName": "Church denomination",
          "invert": false,
          "omitBlank": false,
          "omitError": false,
          "selection": [],
          "selectBlank": true,
          "selectError": false
        }
      ],
      "mode": "row-based"
    },
    "columnName": "Church denomination",
    "expression": "grel:if (cells[\"Orig-copy\"].value.contains(/Associate Reform Presbyterian/), \"Associate Reformed Presbyterian\", \"\")",
    "onError": "keep-original",
    "repeat": false,
    "repeatCount": 10,
    "description": "Text transform on cells in column Church denomination using expression grel:if (cells[\"Orig-copy\"].value.contains(/Associate Reform Presbyterian/), \"Associate Reformed Presbyterian\", \"\")"
  },
  {
    "op": "core/text-transform",
    "engineConfig": {
      "facets": [
        {
          "type": "list",
          "name": "Church",
          "expression": "value",
          "columnName": "Church",
          "invert": false,
          "omitBlank": false,
          "omitError": false,
          "selection": [
            {
              "v": {
                "v": "Church",
                "l": "Church"
              }
            }
          ],
          "selectBlank": false,
          "selectError": false
        },
        {
          "type": "list",
          "name": "Church denomination",
          "expression": "value",
          "columnName": "Church denomination",
          "invert": false,
          "omitBlank": false,
          "omitError": false,
          "selection": [],
          "selectBlank": true,
          "selectError": false
        }
      ],
      "mode": "row-based"
    },
    "columnName": "Name",
    "expression": "grel:value.replace(/Bapt/, \"Baptist\")",
    "onError": "keep-original",
    "repeat": false,
    "repeatCount": 10,
    "description": "Text transform on cells in column Name using expression grel:value.replace(/Bapt/, \"Baptist\")"
  },
  {
    "op": "core/text-transform",
    "engineConfig": {
      "facets": [
        {
          "type": "list",
          "name": "Church",
          "expression": "value",
          "columnName": "Church",
          "invert": false,
          "omitBlank": false,
          "omitError": false,
          "selection": [
            {
              "v": {
                "v": "Church",
                "l": "Church"
              }
            }
          ],
          "selectBlank": false,
          "selectError": false
        },
        {
          "type": "list",
          "name": "Church denomination",
          "expression": "value",
          "columnName": "Church denomination",
          "invert": false,
          "omitBlank": false,
          "omitError": false,
          "selection": [],
          "selectBlank": true,
          "selectError": false
        }
      ],
      "mode": "row-based"
    },
    "columnName": "Name",
    "expression": "grel:value.replace(/Paptist/, \"Baptist\")",
    "onError": "keep-original",
    "repeat": false,
    "repeatCount": 10,
    "description": "Text transform on cells in column Name using expression grel:value.replace(/Paptist/, \"Baptist\")"
  },
  {
    "op": "core/text-transform",
    "engineConfig": {
      "facets": [
        {
          "type": "list",
          "name": "Church",
          "expression": "value",
          "columnName": "Church",
          "invert": false,
          "omitBlank": false,
          "omitError": false,
          "selection": [
            {
              "v": {
                "v": "Church",
                "l": "Church"
              }
            }
          ],
          "selectBlank": false,
          "selectError": false
        },
        {
          "type": "list",
          "name": "Church denomination",
          "expression": "value",
          "columnName": "Church denomination",
          "invert": false,
          "omitBlank": false,
          "omitError": false,
          "selection": [],
          "selectBlank": true,
          "selectError": false
        }
      ],
      "mode": "row-based"
    },
    "columnName": "Church denomination",
    "expression": "grel:if (cells[\"Name\"].value.contains(/Baptist/), \"Baptist\", \"\")",
    "onError": "keep-original",
    "repeat": false,
    "repeatCount": 10,
    "description": "Text transform on cells in column Church denomination using expression grel:if (cells[\"Name\"].value.contains(/Baptist/), \"Baptist\", \"\")"
  },
  {
    "op": "core/text-transform",
    "engineConfig": {
      "facets": [
        {
          "type": "list",
          "name": "Church",
          "expression": "value",
          "columnName": "Church",
          "invert": false,
          "omitBlank": false,
          "omitError": false,
          "selection": [
            {
              "v": {
                "v": "Church",
                "l": "Church"
              }
            }
          ],
          "selectBlank": false,
          "selectError": false
        },
        {
          "type": "list",
          "name": "Church denomination",
          "expression": "value",
          "columnName": "Church denomination",
          "invert": false,
          "omitBlank": false,
          "omitError": false,
          "selection": [],
          "selectBlank": true,
          "selectError": false
        }
      ],
      "mode": "row-based"
    },
    "columnName": "Church denomination",
    "expression": "value.replace(\"\",\"other\")",
    "onError": "keep-original",
    "repeat": false,
    "repeatCount": 10,
    "description": "Text transform on cells in column Church denomination using expression value.replace(\"\",\"other\")"
  },
  {
    "op": "core/text-transform",
    "engineConfig": {
      "facets": [
        {
          "type": "list",
          "name": "Church",
          "expression": "value",
          "columnName": "Church",
          "invert": false,
          "omitBlank": false,
          "omitError": false,
          "selection": [
            {
              "v": {
                "v": "Church",
                "l": "Church"
              }
            }
          ],
          "selectBlank": false,
          "selectError": false
        }
      ],
      "mode": "row-based"
    },
    "columnName": "Biz",
    "expression": "grel:if (cells[\"Church\"].value.contains(/Church/), \"1\", \"\")",
    "onError": "keep-original",
    "repeat": false,
    "repeatCount": 10,
    "description": "Text transform on cells in column Biz using expression grel:if (cells[\"Church\"].value.contains(/Church/), \"1\", \"\")"
  },
  {
    "op": "core/text-transform",
    "engineConfig": {
      "facets": [
        {
          "type": "list",
          "name": "Church",
          "expression": "value",
          "columnName": "Church",
          "invert": false,
          "omitBlank": false,
          "omitError": false,
          "selection": [
            {
              "v": {
                "v": "Church",
                "l": "Church"
              }
            }
          ],
          "selectBlank": false,
          "selectError": false
        }
      ],
      "mode": "row-based"
    },
    "columnName": "Spouse",
    "expression": "null",
    "onError": "keep-original",
    "repeat": false,
    "repeatCount": 10,
    "description": "Text transform on cells in column Spouse using expression null"
  },
  {
    "op": "core/text-transform",
    "engineConfig": {
      "facets": [
        {
          "type": "list",
          "name": "Church",
          "expression": "value",
          "columnName": "Church",
          "invert": false,
          "omitBlank": false,
          "omitError": false,
          "selection": [
            {
              "v": {
                "v": "Church",
                "l": "Church"
              }
            }
          ],
          "selectBlank": false,
          "selectError": false
        }
      ],
      "mode": "row-based"
    },
    "columnName": "Job",
    "expression": "null",
    "onError": "keep-original",
    "repeat": false,
    "repeatCount": 10,
    "description": "Text transform on cells in column Job using expression null"
  },
  {
    "op": "core/text-transform",
    "engineConfig": {
      "facets": [
        {
          "type": "list",
          "name": "Church",
          "expression": "value",
          "columnName": "Church",
          "invert": false,
          "omitBlank": false,
          "omitError": false,
          "selection": [
            {
              "v": {
                "v": "Church",
                "l": "Church"
              }
            }
          ],
          "selectBlank": false,
          "selectError": false
        },
        {
          "type": "list",
          "name": "Company Details",
          "expression": "grel:value",
          "columnName": "Company Details",
          "invert": false,
          "omitBlank": false,
          "omitError": false,
          "selection": [
            {
              "v": {
                "v": "Boulevard cor Templeton av",
                "l": "Boulevard cor Templeton av"
              }
            },
            {
              "v": {
                "v": "Seversville",
                "l": "Seversville"
              }
            },
            {
              "v": {
                "v": "14 s Pegram",
                "l": "14 s Pegram"
              }
            },
            {
              "v": {
                "v": "e 32d, N Charlotte",
                "l": "e 32d, N Charlotte"
              }
            },
            {
              "v": {
                "v": "613 n Davidson",
                "l": "613 n Davidson"
              }
            },
            {
              "v": {
                "v": "Tryon sw tor 6th",
                "l": "Tryon sw tor 6th"
              }
            },
            {
              "v": {
                "v": "406 n Tryon",
                "l": "406 n Tryon"
              }
            },
            {
              "v": {
                "v": "10th av cor Pine",
                "l": "10th av cor Pine"
              }
            },
            {
              "v": {
                "v": "Caldwell cor 9th",
                "l": "Caldwell cor 9th"
              }
            },
            {
              "v": {
                "v": "N Charlotte",
                "l": "N Charlotte"
              }
            },
            {
              "v": {
                "v": "Trade cor Cedar",
                "l": "Trade cor Cedar"
              }
            },
            {
              "v": {
                "v": "e 4th extd",
                "l": "e 4th extd"
              }
            },
            {
              "v": {
                "v": "n Caldwell cor 12th",
                "l": "n Caldwell cor 12th"
              }
            },
            {
              "v": {
                "v": "401-403 s Tryon",
                "l": "401-403 s Tryon"
              }
            },
            {
              "v": {
                "v": "n Tryon sw cor w 7th",
                "l": "n Tryon sw cor w 7th"
              }
            },
            {
              "v": {
                "v": "501 s Tryon",
                "l": "501 s Tryon"
              }
            },
            {
              "v": {
                "v": "1521 s Boulevard",
                "l": "1521 s Boulevard"
              }
            },
            {
              "v": {
                "v": "308 n Graham",
                "l": "308 n Graham"
              }
            },
            {
              "v": {
                "v": "214 n Tryon",
                "l": "214 n Tryon"
              }
            },
            {
              "v": {
                "v": "18 s Cedar",
                "l": "18 s Cedar"
              }
            }
          ],
          "selectBlank": false,
          "selectError": false
        }
      ],
      "mode": "row-based"
    },
    "columnName": "Housing",
    "expression": "grel:cells[\"Company Details\"].value",
    "onError": "keep-original",
    "repeat": false,
    "repeatCount": 10,
    "description": "Text transform on cells in column Housing using expression grel:cells[\"Company Details\"].value"
  },
  {
    "op": "core/text-transform",
    "engineConfig": {
      "facets": [
        {
          "type": "list",
          "name": "Church",
          "expression": "value",
          "columnName": "Church",
          "invert": false,
          "omitBlank": false,
          "omitError": false,
          "selection": [
            {
              "v": {
                "v": "Church",
                "l": "Church"
              }
            }
          ],
          "selectBlank": false,
          "selectError": false
        },
        {
          "type": "list",
          "name": "Company Details",
          "expression": "grel:value",
          "columnName": "Company Details",
          "invert": false,
          "omitBlank": false,
          "omitError": false,
          "selection": [
            {
              "v": {
                "v": "Boulevard cor Templeton av",
                "l": "Boulevard cor Templeton av"
              }
            },
            {
              "v": {
                "v": "Seversville",
                "l": "Seversville"
              }
            },
            {
              "v": {
                "v": "14 s Pegram",
                "l": "14 s Pegram"
              }
            },
            {
              "v": {
                "v": "e 32d, N Charlotte",
                "l": "e 32d, N Charlotte"
              }
            },
            {
              "v": {
                "v": "613 n Davidson",
                "l": "613 n Davidson"
              }
            },
            {
              "v": {
                "v": "Tryon sw tor 6th",
                "l": "Tryon sw tor 6th"
              }
            },
            {
              "v": {
                "v": "406 n Tryon",
                "l": "406 n Tryon"
              }
            },
            {
              "v": {
                "v": "10th av cor Pine",
                "l": "10th av cor Pine"
              }
            },
            {
              "v": {
                "v": "Caldwell cor 9th",
                "l": "Caldwell cor 9th"
              }
            },
            {
              "v": {
                "v": "N Charlotte",
                "l": "N Charlotte"
              }
            },
            {
              "v": {
                "v": "Trade cor Cedar",
                "l": "Trade cor Cedar"
              }
            },
            {
              "v": {
                "v": "e 4th extd",
                "l": "e 4th extd"
              }
            },
            {
              "v": {
                "v": "n Caldwell cor 12th",
                "l": "n Caldwell cor 12th"
              }
            },
            {
              "v": {
                "v": "401-403 s Tryon",
                "l": "401-403 s Tryon"
              }
            },
            {
              "v": {
                "v": "n Tryon sw cor w 7th",
                "l": "n Tryon sw cor w 7th"
              }
            },
            {
              "v": {
                "v": "501 s Tryon",
                "l": "501 s Tryon"
              }
            },
            {
              "v": {
                "v": "1521 s Boulevard",
                "l": "1521 s Boulevard"
              }
            },
            {
              "v": {
                "v": "308 n Graham",
                "l": "308 n Graham"
              }
            },
            {
              "v": {
                "v": "214 n Tryon",
                "l": "214 n Tryon"
              }
            },
            {
              "v": {
                "v": "18 s Cedar",
                "l": "18 s Cedar"
              }
            }
          ],
          "selectBlank": false,
          "selectError": false
        }
      ],
      "mode": "row-based"
    },
    "columnName": "Company Details",
    "expression": "null",
    "onError": "keep-original",
    "repeat": false,
    "repeatCount": 10,
    "description": "Text transform on cells in column Company Details using expression null"
  },
  {
    "op": "core/column-rename",
    "oldColumnName": "Housing",
    "newColumnName": "Address",
    "description": "Rename column Housing to Address"
  },
  {
    "op": "core/text-transform",
    "engineConfig": {
      "facets": [
        {
          "type": "list",
          "name": "Church",
          "expression": "value",
          "columnName": "Church",
          "invert": false,
          "omitBlank": false,
          "omitError": false,
          "selection": [
            {
              "v": {
                "v": "Church",
                "l": "Church"
              }
            }
          ],
          "selectBlank": false,
          "selectError": false
        },
        {
          "type": "list",
          "name": "Company",
          "expression": "value",
          "columnName": "Company",
          "invert": false,
          "omitBlank": false,
          "omitError": false,
          "selection": [
            {
              "v": {
                "v": "Rev Jno Clement",
                "l": "Rev Jno Clement"
              }
            },
            {
              "v": {
                "v": "Rev Alonzo Spaulding",
                "l": "Rev Alonzo Spaulding"
              }
            },
            {
              "v": {
                "v": "Rev H H Hulton",
                "l": "Rev H H Hulton"
              }
            },
            {
              "v": {
                "v": "Rev E L Madison",
                "l": "Rev E L Madison"
              }
            },
            {
              "v": {
                "v": "Rev G O Bullock",
                "l": "Rev G O Bullock"
              }
            },
            {
              "v": {
                "v": "Rev J R Cozart",
                "l": "Rev J R Cozart"
              }
            },
            {
              "v": {
                "v": "Rev C N Jenkins",
                "l": "Rev C N Jenkins"
              }
            },
            {
              "v": {
                "v": "Rev W J Smith",
                "l": "Rev W J Smith"
              }
            },
            {
              "v": {
                "v": "Rev A T Bell",
                "l": "Rev A T Bell"
              }
            },
            {
              "v": {
                "v": "Rev Harris Mallinckrodt",
                "l": "Rev Harris Mallinckrodt"
              }
            },
            {
              "v": {
                "v": "Rev P S Lewis",
                "l": "Rev P S Lewis"
              }
            },
            {
              "v": {
                "v": "Rev Jno Mercer",
                "l": "Rev Jno Mercer"
              }
            },
            {
              "v": {
                "v": "Rev T D Cartledge",
                "l": "Rev T D Cartledge"
              }
            },
            {
              "v": {
                "v": "Rev W O Goode",
                "l": "Rev W O Goode"
              }
            },
            {
              "v": {
                "v": "W E Furr",
                "l": "W E Furr"
              }
            },
            {
              "v": {
                "v": "Rev J P Foote",
                "l": "Rev J P Foote"
              }
            },
            {
              "v": {
                "v": "Rev A W Plyler",
                "l": "Rev A W Plyler"
              }
            },
            {
              "v": {
                "v": "Rev E G Carson",
                "l": "Rev E G Carson"
              }
            },
            {
              "v": {
                "v": "Rev G T Rowe",
                "l": "Rev G T Rowe"
              }
            },
            {
              "v": {
                "v": "Rev L R Pruett",
                "l": "Rev L R Pruett"
              }
            },
            {
              "v": {
                "v": "Rev A F Graham",
                "l": "Rev A F Graham"
              }
            },
            {
              "v": {
                "v": "Rev E E Hough",
                "l": "Rev E E Hough"
              }
            },
            {
              "v": {
                "v": "Rev W M Scott",
                "l": "Rev W M Scott"
              }
            },
            {
              "v": {
                "v": "Rev W E West",
                "l": "Rev W E West"
              }
            },
            {
              "v": {
                "v": "Rev Francis Osborne",
                "l": "Rev Francis Osborne"
              }
            },
            {
              "v": {
                "v": "Rev W M Robbins",
                "l": "Rev W M Robbins"
              }
            },
            {
              "v": {
                "v": "Rev J S Smith",
                "l": "Rev J S Smith"
              }
            },
            {
              "v": {
                "v": "Rev H M Pressley",
                "l": "Rev H M Pressley"
              }
            },
            {
              "v": {
                "v": "Rev W C Cleland",
                "l": "Rev W C Cleland"
              }
            },
            {
              "v": {
                "v": "Rev R L Patterson",
                "l": "Rev R L Patterson"
              }
            },
            {
              "v": {
                "v": "Rev S W Hamilton",
                "l": "Rev S W Hamilton"
              }
            },
            {
              "v": {
                "v": "Rev Geo Dixon",
                "l": "Rev Geo Dixon"
              }
            },
            {
              "v": {
                "v": "Rev A A McGeachy",
                "l": "Rev A A McGeachy"
              }
            },
            {
              "v": {
                "v": "Rev A M Cochran",
                "l": "Rev A M Cochran"
              }
            },
            {
              "v": {
                "v": "Rev Jno McDavid",
                "l": "Rev Jno McDavid"
              }
            },
            {
              "v": {
                "v": "Rev Jos Mueller",
                "l": "Rev Jos Mueller"
              }
            },
            {
              "v": {
                "v": "Rev C K Brown",
                "l": "Rev C K Brown"
              }
            },
            {
              "v": {
                "v": "Rev L A Falls",
                "l": "Rev L A Falls"
              }
            },
            {
              "v": {
                "v": "Rev W C Jones",
                "l": "Rev W C Jones"
              }
            },
            {
              "v": {
                "v": "Rev Wm De Bose",
                "l": "Rev Wm De Bose"
              }
            },
            {
              "v": {
                "v": "Rev C F Gingles",
                "l": "Rev C F Gingles"
              }
            },
            {
              "v": {
                "v": "Rev S F Conrad",
                "l": "Rev S F Conrad"
              }
            },
            {
              "v": {
                "v": "Rev D J Flynn",
                "l": "Rev D J Flynn"
              }
            },
            {
              "v": {
                "v": "Rev G W Hanna",
                "l": "Rev G W Hanna"
              }
            },
            {
              "v": {
                "v": "Rev David Thompson",
                "l": "Rev David Thompson"
              }
            },
            {
              "v": {
                "v": "Rev Harris Mallinnkrodt",
                "l": "Rev Harris Mallinnkrodt"
              }
            },
            {
              "v": {
                "v": "Rev R R Caldwell",
                "l": "Rev R R Caldwell"
              }
            },
            {
              "v": {
                "v": "Rev J C Gillespie",
                "l": "Rev J C Gillespie"
              }
            },
            {
              "v": {
                "v": "Rev Edwd E Bomar",
                "l": "Rev Edwd E Bomar"
              }
            }
          ],
          "selectBlank": false,
          "selectError": false
        }
      ],
      "mode": "row-based"
    },
    "columnName": "Company Details",
    "expression": "grel:cells[\"Company\"].value",
    "onError": "keep-original",
    "repeat": false,
    "repeatCount": 10,
    "description": "Text transform on cells in column Company Details using expression grel:cells[\"Company\"].value"
  },
  {
    "op": "core/text-transform",
    "engineConfig": {
      "facets": [
        {
          "type": "list",
          "name": "Church",
          "expression": "value",
          "columnName": "Church",
          "invert": false,
          "omitBlank": false,
          "omitError": false,
          "selection": [
            {
              "v": {
                "v": "Church",
                "l": "Church"
              }
            }
          ],
          "selectBlank": false,
          "selectError": false
        },
        {
          "type": "list",
          "name": "Company",
          "expression": "value.split(' ')",
          "columnName": "Company",
          "invert": false,
          "omitBlank": false,
          "omitError": false,
          "selection": [
            {
              "v": {
                "v": "Rev",
                "l": "Rev"
              }
            }
          ],
          "selectBlank": false,
          "selectError": false
        }
      ],
      "mode": "row-based"
    },
    "columnName": "Company",
    "expression": "null",
    "onError": "keep-original",
    "repeat": false,
    "repeatCount": 10,
    "description": "Text transform on cells in column Company using expression null"
  },
  {
    "op": "core/text-transform",
    "engineConfig": {
      "facets": [
        {
          "type": "list",
          "name": "Church",
          "expression": "value",
          "columnName": "Church",
          "invert": false,
          "omitBlank": false,
          "omitError": false,
          "selection": [
            {
              "v": {
                "v": "Church",
                "l": "Church"
              }
            }
          ],
          "selectBlank": false,
          "selectError": false
        }
      ],
      "mode": "row-based"
    },
    "columnName": "Company",
    "expression": "grel:cells[\"Name\"].value",
    "onError": "keep-original",
    "repeat": false,
    "repeatCount": 10,
    "description": "Text transform on cells in column Company using expression grel:cells[\"Name\"].value"
  }
]